{"content":[{"id":"5fce1f70","settings":{"structure":"30","padding":{"unit":"px","top":"30","right":"10","bottom":"30","left":"10","isLinked":false}},"elements":[{"id":"438a27d6","settings":{"_column_size":33,"_inline_size":null},"elements":[{"id":"2dd73f66","settings":{"date_time_layout_style":"date-time-style-10","secondary_color":"#21801F","date_color":"#FFFFFF","date_icon_color":"#FFFFFF","before_date_color":"#FFFFFF","after_date_color":"#FFFFFF"},"elements":[],"isInner":false,"widgetType":"date-time","elType":"widget"}],"isInner":false,"elType":"column"},{"id":"2ac8ce5","settings":{"_column_size":33,"_inline_size":null},"elements":[],"isInner":false,"elType":"column"},{"id":"57ea02b7","settings":{"_column_size":33,"_inline_size":null},"elements":[],"isInner":false,"elType":"column"}],"isInner":false,"elType":"section"}],"page_settings":[],"version":"0.4","title":"date-time-9","type":"section"}